README.txt
setup.py
collective/__init__.py
collective.portlet.contribute.egg-info/PKG-INFO
collective.portlet.contribute.egg-info/SOURCES.txt
collective.portlet.contribute.egg-info/dependency_links.txt
collective.portlet.contribute.egg-info/entry_points.txt
collective.portlet.contribute.egg-info/namespace_packages.txt
collective.portlet.contribute.egg-info/not-zip-safe
collective.portlet.contribute.egg-info/requires.txt
collective.portlet.contribute.egg-info/top_level.txt
collective/portlet/__init__.py
collective/portlet/contribute/__init__.py
collective/portlet/contribute/browser.py
collective/portlet/contribute/configure.zcml
collective/portlet/contribute/contributecontent.pt
collective/portlet/contribute/contributecontent.py
collective/portlet/contribute/profiles/default/metadata.xml
collective/portlet/contribute/profiles/default/portlets.xml
collective/portlet/contribute/profiles/default/rolemap.xml
collective/portlet/contribute/tests/__init__.py
collective/portlet/contribute/tests/base.py
collective/portlet/contribute/tests/test_portlet.py
docs/HISTORY.txt
docs/INSTALL.txt
docs/LICENSE.GPL
docs/LICENSE.txt