Metadata-Version: 1.0
Name: collective.portlet.contribute
Version: 1.0b1
Summary: A portlet to let people add content of a given type in a folder
Home-page: http://pypi.python.org/pypi/collective.portlet.contribute
Author: Martin Aspeli
Author-email: optilude@gmail.com
License: GPL
Keywords: plone portlet contribute content
Platform: UNKNOWN
Classifier: Framework :: Plone
Classifier: Programming Language :: Python
Classifier: Topic :: Software Development :: Libraries :: Python Modules
